signaltour/Analysis.py
signaltour/Plot.py
signaltour/Signal.py
signaltour/__init__.py
signaltour/_Analysis_Module/ModeAnalysis.py
signaltour/_Analysis_Module/SpectrumAnalysis.py
signaltour/_Analysis_Module/StatsTrendAnalysis.py
signaltour/_Analysis_Module/TimeFreqAnalysis.py
signaltour/_Analysis_Module/WaveletAnalysis.py
signaltour/_Analysis_Module/__init__.py
signaltour/_Analysis_Module/core.py
signaltour/_Assist_Module/Dependencies.py
signaltour/_Assist_Module/__init__.py
signaltour/_Assist_Module/times+simsun.ttf
signaltour/_Plot_Module/ImagePlot.py
signaltour/_Plot_Module/LinePlot.py
signaltour/_Plot_Module/PlotPlugin.py
signaltour/_Plot_Module/__init__.py
signaltour/_Plot_Module/core.py
signaltour/_Signal_Module/SignalFilt.py
signaltour/_Signal_Module/SignalRead.py
signaltour/_Signal_Module/SignalSample.py
signaltour/_Signal_Module/SignalSimulate.py
signaltour/_Signal_Module/__init__.py
signaltour/_Signal_Module/core.py
signaltour-1.1.0.dist-info/licenses/LICENSE
signaltour-1.1.0.dist-info/METADATA
signaltour-1.1.0.dist-info/WHEEL
signaltour-1.1.0.dist-info/top_level.txt
signaltour-1.1.0.dist-info/RECORD
