Metadata-Version: 2.4
Name: signaltour
Version: 1.1.0
Summary: Python package for the whole process of signal loading management, preprocessing, in-depth analysis and visualization of one-dimensional time series oscillation data
Author-email: Xiong Chengwen <xiongcw1129@gmail.com>
License: Apache-2.0
Requires-Python: >=3.11
License-File: LICENSE
Requires-Dist: numpy>=2.0.0
Requires-Dist: scipy>=1.14.0
Requires-Dist: matplotlib>=3.9.0
Requires-Dist: pandas>=2.2.2
Requires-Dist: anytree>=2.13.0
Requires-Dist: pyarrow>=22.0.0
Provides-Extra: dev
Requires-Dist: marimo>=0.18.4; extra == "dev"
Requires-Dist: pytest>=9.0.2; extra == "dev"
Requires-Dist: pytest-cov>=7.0.0; extra == "dev"
Requires-Dist: ruff>=0.14.11; extra == "dev"
Requires-Dist: ty>=0.0.11; extra == "dev"
Dynamic: license-file
